LICENSE
README.rst
hotness_schema/__init__.py
hotness_schema/messages.py
hotness_schema/tests/__init__.py
hotness_schema/tests/fixtures/org.fedoraproject.prod.hotness.update.bug.file.json
hotness_schema/tests/fixtures/org.fedoraproject.prod.hotness.update.drop.json
hotness_schema/tests/test_messages.py
hotness_schema/tests/test_schema.py
fedora_messaging_the_new_hotness_schema-1.2.0.dist-info/LICENSE
fedora_messaging_the_new_hotness_schema-1.2.0.dist-info/METADATA
fedora_messaging_the_new_hotness_schema-1.2.0.dist-info/WHEEL
fedora_messaging_the_new_hotness_schema-1.2.0.dist-info/entry_points.txt
fedora_messaging_the_new_hotness_schema-1.2.0.dist-info/RECORD
